README.md
setup.py
bin/new-contributor-wizard
new_contributor_wizard/__init__.py
new_contributor_wizard/main.py
new_contributor_wizard/settings.py
new_contributor_wizard.egg-info/PKG-INFO
new_contributor_wizard.egg-info/SOURCES.txt
new_contributor_wizard.egg-info/dependency_links.txt
new_contributor_wizard.egg-info/requires.txt
new_contributor_wizard.egg-info/top_level.txt
new_contributor_wizard/data/module_data.json
new_contributor_wizard/libs/__init__.py
new_contributor_wizard/libs/garden/__init__.py
new_contributor_wizard/libs/garden/navigationdrawer/LICENSE
new_contributor_wizard/libs/garden/navigationdrawer/README.md
new_contributor_wizard/libs/garden/navigationdrawer/__init__.py
new_contributor_wizard/libs/garden/navigationdrawer/navigationdrawer_closed.png
new_contributor_wizard/libs/garden/navigationdrawer/navigationdrawer_gradient_ltor.png
new_contributor_wizard/libs/garden/navigationdrawer/navigationdrawer_gradient_rtol.png
new_contributor_wizard/libs/garden/navigationdrawer/navigationdrawer_open_example1.png
new_contributor_wizard/libs/garden/navigationdrawer/navigationdrawer_open_example2.png
new_contributor_wizard/libs/garden/navigationdrawer/screenshot.png
new_contributor_wizard/modules/__init__.py
new_contributor_wizard/modules/course_modules/__init__.py
new_contributor_wizard/modules/course_modules/blog/__init__.py
new_contributor_wizard/modules/course_modules/blog/blog.py
new_contributor_wizard/modules/course_modules/blog/tools/__init__.py
new_contributor_wizard/modules/course_modules/command_line_inteface/__init__.py
new_contributor_wizard/modules/course_modules/command_line_inteface/command_line_inteface.py
new_contributor_wizard/modules/course_modules/command_line_inteface/tools/__init__.py
new_contributor_wizard/modules/course_modules/communication/__init__.py
new_contributor_wizard/modules/course_modules/communication/communication.py
new_contributor_wizard/modules/course_modules/communication/tools/__init__.py
new_contributor_wizard/modules/course_modules/encryption/__init__.py
new_contributor_wizard/modules/course_modules/encryption/encryption.py
new_contributor_wizard/modules/course_modules/encryption/tools/__init__.py
