Metadata-Version: 2.1
Name: new-contributor-wizard
Version: 0.0.5
Summary: New Contributor Wizard is a GUI application build to help new contributors get started with Open Source.
Home-page: https://salsa.debian.org/new-contributor-wizard-team/new-contributor-wizard
Author: Shashank Kumar
Author-email: shashankkumarkushwaha@gmail.com
License: UNKNOWN
Platform: UNKNOWN
Classifier: Programming Language :: Python :: 3.5
Classifier: License :: OSI Approved :: GNU General Public License v3 (GPLv3)
Classifier: Operating System :: OS Independent
